cli/__init__.py
cli/main.py
cli/commands/__init__.py
cli/commands/browser.py
cli/commands/describe.py
cli/commands/email.py
cli/commands/network.py
cli/commands/utils.py
core/__init__.py
core/registry.py
core/browser/browser_history.py
core/browser/common_words.py
core/browser/downloads_history.py
core/browser/fav_screen.py
core/browser/logins.py
core/browser/unusual_patterns.py
core/data/__init__.py
core/data/data_recovery.py
core/db/db.py
core/email/email_parser.py
core/email/header_analysis.py
core/models/orm.py
core/models/schemas.py
core/network/__init__.py
core/network/arp_scan.py
core/network/dns_recon.py
core/network/fingerprinting.py
core/network/ip_info.py
core/network/network_map.py
core/network/ping_sweep.py
core/network/port_scanner.py
core/network/smb_scan.py
core/network/snmp_scan.py
core/network/traceroute.py
core/network/utils.py
core/utils/__init__.py
core/utils/gerar_amostras.py
forensic_cli-1.4.6.dist-info/licenses/LICENSE
forensic_cli-1.4.6.dist-info/licenses/LICENSE-GPL
forensic_cli-1.4.6.dist-info/METADATA
forensic_cli-1.4.6.dist-info/WHEEL
forensic_cli-1.4.6.dist-info/entry_points.txt
forensic_cli-1.4.6.dist-info/top_level.txt
forensic_cli-1.4.6.dist-info/RECORD
