Metadata-Version: 2.4
Name: forensic-cli
Version: 1.4.6
Summary: DevKit Forense - CLI para análise de navegadores e rede
Home-page: https://github.com/ErickG123/devkit_forense
Author: Erick Gabriel dos Santos Alves
Author-email: Erick Gabriel dos Santos Alves <erickgabrielalves0@gmail.com>
License: MIT
Project-URL: Changelog, https://erickg123.github.io/devkit_forense/
Project-URL: Source, https://github.com/ErickG123/devkit_forense
Project-URL: Issues, https://github.com/ErickG123/devkit_forense/issues
Keywords: forensics,cli,network,browser
Requires-Python: >=3.11
License-File: LICENSE
License-File: LICENSE-GPL
Requires-Dist: altgraph==0.17.4
Requires-Dist: annotated-types==0.7.0
Requires-Dist: anyio==4.10.0
Requires-Dist: attrs==25.3.0
Requires-Dist: certifi==2025.8.3
Requires-Dist: cffi==1.17.1
Requires-Dist: charset-normalizer==3.4.3
Requires-Dist: click==8.2.1
Requires-Dist: colorama==0.4.6
Requires-Dist: contourpy==1.3.3
Requires-Dist: cryptography==45.0.6
Requires-Dist: cycler==0.12.1
Requires-Dist: defusedxml==0.7.1
Requires-Dist: dnspython==2.7.0
Requires-Dist: docopt==0.6.2
Requires-Dist: docutils==0.22
Requires-Dist: fonttools==4.59.1
Requires-Dist: greenlet==3.2.4
Requires-Dist: h11==0.16.0
Requires-Dist: id==1.5.0
Requires-Dist: idna==3.10
Requires-Dist: ipwhois==1.3.0
Requires-Dist: jaraco.classes==3.4.0
Requires-Dist: jaraco.context==6.0.1
Requires-Dist: jaraco.functools==4.3.0
Requires-Dist: keyring==25.6.0
Requires-Dist: kiwisolver==1.4.9
Requires-Dist: markdown-it-py==4.0.0
Requires-Dist: matplotlib==3.10.5
Requires-Dist: mdurl==0.1.2
Requires-Dist: more-itertools==10.7.0
Requires-Dist: nh3==0.3.0
Requires-Dist: numpy==2.3.2
Requires-Dist: outcome==1.3.0.post0
Requires-Dist: packaging==25.0
Requires-Dist: pandas==2.3.2
Requires-Dist: pefile==2023.2.7
Requires-Dist: pillow==11.3.0
Requires-Dist: pyasn1==0.6.1
Requires-Dist: pycparser==2.22
Requires-Dist: pycryptodome==3.23.0
Requires-Dist: pydantic==2.11.7
Requires-Dist: pydantic_core==2.33.2
Requires-Dist: pyinstaller==6.15.0
Requires-Dist: pyinstaller-hooks-contrib==2025.8
Requires-Dist: pyparsing==3.2.3
Requires-Dist: pysnmp==7.1.21
Requires-Dist: PySocks==1.7.1
Requires-Dist: pyspnego==0.11.2
Requires-Dist: python-dateutil==2.9.0.post0
Requires-Dist: pytz==2025.2
Requires-Dist: pywin32==311
Requires-Dist: pywin32-ctypes==0.2.3
Requires-Dist: requests==2.32.5
Requires-Dist: requests-toolbelt==1.0.0
Requires-Dist: rfc3986==2.0.0
Requires-Dist: rich==14.1.0
Requires-Dist: scapy==2.6.1
Requires-Dist: selenium==4.35.0
Requires-Dist: six==1.17.0
Requires-Dist: smbprotocol==1.15.0
Requires-Dist: sniffio==1.3.1
Requires-Dist: sortedcontainers==2.4.0
Requires-Dist: starlette==0.47.2
Requires-Dist: trio==0.30.0
Requires-Dist: trio-websocket==0.12.2
Requires-Dist: typer==0.16.1
Requires-Dist: typing-inspection==0.4.1
Requires-Dist: typing_extensions==4.14.1
Requires-Dist: tzdata==2025.2
Requires-Dist: urllib3==2.5.0
Requires-Dist: websocket-client==1.8.0
Requires-Dist: wsproto==1.2.0
Requires-Dist: yarg==0.1.10
Dynamic: author
Dynamic: home-page
Dynamic: license-file
Dynamic: requires-python
